LICENSE
MANIFEST.in
README.rst
setup.py
django_bootstrap_dynamic_formsets/__init__.py
django_bootstrap_dynamic_formsets.egg-info/PKG-INFO
django_bootstrap_dynamic_formsets.egg-info/SOURCES.txt
django_bootstrap_dynamic_formsets.egg-info/dependency_links.txt
django_bootstrap_dynamic_formsets.egg-info/requires.txt
django_bootstrap_dynamic_formsets.egg-info/top_level.txt
django_bootstrap_dynamic_formsets/static/django_bootstrap_dynamic_formsets/extra.css
django_bootstrap_dynamic_formsets/templates/django_bootstrap_dynamic_formsets/dynamic_formsets.html
django_bootstrap_dynamic_formsets/templates/django_bootstrap_dynamic_formsets/dynamic_formsets_js.html
django_bootstrap_dynamic_formsets/templatetags/__init__.py
django_bootstrap_dynamic_formsets/templatetags/bootstrap_dynamic_formsets.py