Metadata-Version: 1.1
Name: django-bootstrap-dynamic-formsets
Version: 0.4.5
Summary: JavaScript-enhanced dynamic formsets using Bootstrap
Home-page: https://github.com/FHBrandenburg/django-bootstrap-dynamic-formsets
Author: Daniel Weis
Author-email: weisd@fh-brandenburg.de
License: MIT License
Platform: UNKNOWN
Classifier: Environment :: Web Environment
Classifier: Framework :: Django
Classifier: Intended Audience :: Developers
Classifier: License :: OSI Approved :: MIT License
Classifier: Operating System :: OS Independent
Classifier: Programming Language :: Python
Classifier: Topic :: Internet :: WWW/HTTP
